simcats/__init__.py
simcats/_default_configs.py
simcats/_simulation.py
simcats/distortions/__init__.py
simcats/distortions/_distortion_interfaces.py
simcats/distortions/_dot_jumps.py
simcats/distortions/_pink_noise.py
simcats/distortions/_random_telegraph_noise.py
simcats/distortions/_transition_blurring.py
simcats/distortions/_white_noise.py
simcats/ideal_csd/__init__.py
simcats/ideal_csd/_ideal_csd_interface.py
simcats/ideal_csd/geometric/__init__.py
simcats/ideal_csd/geometric/_calculate_all_bezier_anchors.py
simcats/ideal_csd/geometric/_generate_lead_transition_mask.py
simcats/ideal_csd/geometric/_get_electron_occupation.py
simcats/ideal_csd/geometric/_ideal_csd_geometric.py
simcats/ideal_csd/geometric/_ideal_csd_geometric_class.py
simcats/ideal_csd/geometric/_initialize_tct_functions.py
simcats/ideal_csd/geometric/_tct_bezier.py
simcats/sensor/__init__.py
simcats/sensor/_gaussian_sensor_peak.py
simcats/sensor/_generic_sensor.py
simcats/sensor/_lorentzian_sensor_peak.py
simcats/sensor/_sensor_interface.py
simcats/support_functions/__init__.py
simcats/support_functions/_cumulative_distribution_functions.py
simcats/support_functions/_fermi_filter1d.py
simcats/support_functions/_parameter_sampling.py
simcats/support_functions/_plotting.py
simcats/support_functions/_rotate_points.py
simcats/support_functions/_signed_dist_points_line.py
simcats-1.2.0.dist-info/LICENSE
simcats-1.2.0.dist-info/METADATA
simcats-1.2.0.dist-info/WHEEL
simcats-1.2.0.dist-info/top_level.txt
simcats-1.2.0.dist-info/RECORD
