Metadata-Version: 2.1
Name: simcats
Version: 1.2.0
Summary: SimCATS is a python framework for simulating charge stability diagrams (CSDs) typically measured during the tuning process of qubits.
Author-email: Fabian Hader <f.hader@fz-juelich.de>, Sarah Fleitmann <s.fleitmann@fz-juelich.de>, Fabian Fuchs <f.fuchs@fz-juelich.de>
License: CC BY-NC-SA 4.0
Project-URL: homepage, https://github.com/f-hader/SimCATS
Project-URL: documentation, https://simcats.readthedocs.io
Project-URL: source, https://github.com/f-hader/SimCATS
Project-URL: tracker, https://github.com/f-hader/SimCATS/issues
Classifier: Development Status :: 5 - Production/Stable
Classifier: Intended Audience :: Science/Research
Classifier: Programming Language :: Python
Classifier: Programming Language :: Python :: 3
Classifier: Programming Language :: Python :: 3.7
Classifier: Programming Language :: Python :: 3.8
Classifier: Programming Language :: Python :: 3.9
Classifier: Programming Language :: Python :: 3.10
Classifier: Programming Language :: Python :: 3.11
Classifier: Topic :: Scientific/Engineering
Classifier: Typing :: Typed
Requires-Python: >=3.7
License-File: LICENSE
Requires-Dist: bezier
Requires-Dist: colorednoise
Requires-Dist: diplib
Requires-Dist: matplotlib
Requires-Dist: numpy
Requires-Dist: opencv-python
Requires-Dist: scipy
Requires-Dist: sympy
